contextual_logger/__init__.py
contextual_logger/logger.py
contextual_logger-0.0.2.dist-info/LICENSE.txt
contextual_logger-0.0.2.dist-info/METADATA
contextual_logger-0.0.2.dist-info/WHEEL
contextual_logger-0.0.2.dist-info/top_level.txt
contextual_logger-0.0.2.dist-info/RECORD
