Metadata-Version: 2.1
Name: contextual-logger
Version: 0.0.2
Summary: Contextual Logger
Home-page: https://github.com/blester125/contextual-logger
Download-URL: https://github.com/blester125/contextual-logger/archive/0.0.2.tar.gz
Author: blester125
Author-email: blester125@gmail.com
License: MIT
Classifier: Development Status :: 3 - Alpha
Classifier: Intended Audience :: Science/Research
Classifier: License :: OSI Approved :: MIT License
Classifier: Intended Audience :: Developers
Classifier: Natural Language :: English
Classifier: Topic :: Scientific/Engineering
Classifier: Environment :: Console
Classifier: Programming Language :: Python :: 3 :: Only
Requires-Python: >=3.6
License-File: LICENSE.txt
Provides-Extra: test
Requires-Dist: pytest; extra == "test"
